EXTERNALS.txt
README.txt
setup.cfg
setup.py
ez_setup/README.txt
ez_setup/__init__.py
releasemanager/__init__.py
releasemanager/web/__init__.py
releasemanager/web/console/__init__.py
releasemanager/web/console/release.py
releasemanager/web/console/websetup.py
releasemanager/web/console/config/__init__.py
releasemanager/web/console/config/environment.py
releasemanager/web/console/config/middleware.py
releasemanager/web/console/config/routing.py
releasemanager/web/console/controllers/__init__.py
releasemanager/web/console/controllers/error.py
releasemanager/web/console/controllers/login.py
releasemanager/web/console/controllers/main.py
releasemanager/web/console/controllers/managers.py
releasemanager/web/console/controllers/monitor.py
releasemanager/web/console/controllers/template.py
releasemanager/web/console/ctl/__init__.py
releasemanager/web/console/ctl/generate.py
releasemanager/web/console/ctl/templates/__init__.py
releasemanager/web/console/ctl/templates/apache.conf
releasemanager/web/console/ctl/templates/development.ini
releasemanager/web/console/ctl/templates/plugins/conf/__init__.py
releasemanager/web/console/ctl/templates/plugins/conf/auth/__init__.py
releasemanager/web/console/ctl/templates/plugins/conf/auth/plugin_auth_admin.xml
releasemanager/web/console/ctl/templates/plugins/conf/auth/plugin_auth_simpleauth.xml
releasemanager/web/console/docs/index.txt
releasemanager/web/console/i18n/__init__.py
releasemanager/web/console/lib/__init__.py
releasemanager/web/console/lib/app_globals.py
releasemanager/web/console/lib/base.py
releasemanager/web/console/lib/helpers.py
releasemanager/web/console/models/__init__.py
releasemanager/web/console/models/base.py
releasemanager/web/console/models/builders.py
releasemanager/web/console/models/installers.py
releasemanager/web/console/models/managers.py
releasemanager/web/console/models/transactions.py
releasemanager/web/console/plugins/__init__.py
releasemanager/web/console/plugins/auth/__init__.py
relman_webconsole.egg-info/PKG-INFO
relman_webconsole.egg-info/SOURCES.txt
relman_webconsole.egg-info/dependency_links.txt
relman_webconsole.egg-info/entry_points.txt
relman_webconsole.egg-info/namespace_packages.txt
relman_webconsole.egg-info/not-zip-safe
relman_webconsole.egg-info/requires.txt
relman_webconsole.egg-info/top_level.txt
