Metadata-Version: 1.0
Name: relman-webconsole
Version: 0.8
Summary: ReleaseManager WebConsole, for simple end-user access.
Home-page: http://code.google.com/p/releasemanager/
Author: James Taylor
Author-email: baldtrol@gmail.com
License: UNKNOWN
Keywords: releasemanager.web
Platform: UNKNOWN
